olympict/__init__.py
olympict/files/__init__.py
olympict/files/o_batch.py
olympict/files/o_file.py
olympict/files/o_image.py
olympict/files/o_video.py
olympict/helpers/batch_tasker.py
olympict/helpers/img_rescaler.py
olympict/helpers/img_resizer.py
olympict/image_tools.py
olympict/object_pipeline.py
olympict/pipeline.py
olympict/pipelines.py
olympict/py.typed
olympict/types.py
olympict/utils/bbox_abs_painter.py
olympict/utils/bbox_hf_painter.py
olympict/utils/crop_op.py
olympict/utils/debug_window.py
olympict/utils/discarder_op.py
olympict/utils/extension_op.py
olympict/utils/folder_op.py
olympict/utils/heatmap_op.py
olympict/utils/huggingface_op.py
olympict/utils/image_op.py
olympict/utils/line_abs_op.py
olympict/utils/line_rel_op.py
olympict/utils/path_op.py
olympict/utils/polygon_abs_op.py
olympict/utils/polygon_rel_op.py
olympict/utils/random_crop_op.py
olympict/utils/saver.py
olympict/utils/segmentation_op.py
olympict/utils/video_sequencer_op.py
olympict/video_saver.py
olympict-1.4.0.dist-info/LICENSE
olympict-1.4.0.dist-info/METADATA
olympict-1.4.0.dist-info/WHEEL
olympict-1.4.0.dist-info/RECORD
