Metadata-Version: 2.1
Name: olympict
Version: 1.4.0
Summary: A powerful parallel pipelining tool for image processing
Home-page: https://gitlab.com/gabraken/olympict
License: MIT
Keywords: image,parallel,multiprocessing,pipeline
Author: Gabriel Kasser
Author-email: gabriel.kasser@gmail.com
Requires-Python: >=3.9,<3.13
Classifier: License :: OSI Approved :: MIT License
Classifier: Programming Language :: Python :: 3
Classifier: Programming Language :: Python :: 3.9
Classifier: Programming Language :: Python :: 3.10
Classifier: Programming Language :: Python :: 3.11
Classifier: Programming Language :: Python :: 3.12
Provides-Extra: hf
Requires-Dist: huggingface-hub (>=0.16.4,<0.17.0) ; extra == "hf"
Requires-Dist: natsort (>=8.3.1,<9.0.0)
Requires-Dist: numpy (>=1.26.1,<2.0.0)
Requires-Dist: olympipe (>=1.4.0)
Requires-Dist: opencv-python (>=4.5)
Requires-Dist: opencv-stubs (>=0.0.8,<0.0.9)
Requires-Dist: pillow (>=10.1.0,<11.0.0) ; extra == "hf"
Requires-Dist: setuptools (>=68.2.2,<69.0.0)
Requires-Dist: timm (>=0.9.10,<0.10.0) ; extra == "hf"
Requires-Dist: torch (>=2.0.0,!=2.0.1,!=2.1.0) ; extra == "hf"
Requires-Dist: transformers (>=4.34.1,<5.0.0) ; extra == "hf"
Project-URL: Documentation, https://gitlab.com/gabraken/olympict/-/blob/master/README.md
Project-URL: Repository, https://gitlab.com/gabraken/olympict
